ggps/__init__.py
ggps/base_handler.py
ggps/counter.py
ggps/gpx_handler.py
ggps/path_handler.py
ggps/tcx_handler.py
ggps/trackpoint.py
ggps-0.5.1.dist-info/METADATA
ggps-0.5.1.dist-info/WHEEL
ggps-0.5.1.dist-info/licenses/LICENSE
ggps-0.5.1.dist-info/RECORD
