Metadata-Version: 2.3
Name: ggps
Version: 0.5.1
Summary: ggps - tcx and gpx file parsing for garmin connect and garmin devices
Project-URL: Homepage, https://github.com/cjoakim/ggps-py
Project-URL: Issues, https://github.com/cjoakim/ggps-py/issues
Project-URL: Repository, https://github.com/cjoakim/ggps-py.git
Author-email: Chris Joakim <christopher.joakim@gmail.com>
Maintainer-email: Chris Joakim <christopher.joakim@gmail.com>
License: MIT License
License-File: LICENSE
Keywords: files,garmin,gps,gpx,parse,running,tcx
Classifier: License :: OSI Approved :: MIT License
Classifier: Operating System :: OS Independent
Classifier: Programming Language :: Python :: 3
Requires-Python: >=3.11
